{
  "as_of": "2026-03-06 15:08:03",
  "currency": "KRW",
  "positions": [
    {
      "symbol": "034020",
      "name": "두산에너빌리티",
      "side": "LONG",
      "qty": 2100.0,
      "avg_price": 97440.0,
      "group": "두산에너빌리티",
      "last_price": 98000,
      "exposure": 204624000.0,
      "mv": 205800000.0,
      "pnl": 1176000.0,
      "pnl_ratio": 0.005747126436781609
    },
    {
      "symbol": "035720",
      "name": "카카오",
      "side": "LONG",
      "qty": 1580.0,
      "avg_price": 62620.0,
      "group": "카카오",
      "last_price": 53500,
      "exposure": 98939600.0,
      "mv": 84530000.0,
      "pnl": -14409600.0,
      "pnl_ratio": -0.14564037048866177
    },
    {
      "symbol": "440110",
      "name": "파두",
      "side": "LONG",
      "qty": 29000.0,
      "avg_price": 19120.0,
      "group": "파두",
      "last_price": 70300,
      "exposure": 554480000.0,
      "mv": 2038700000.0,
      "pnl": 1484220000.0,
      "pnl_ratio": 2.676778242677824
    },
    {
      "symbol": "000210",
      "name": "DL",
      "side": "LONG",
      "qty": 7183.0,
      "avg_price": 56496.0,
      "group": "DL",
      "last_price": 43600,
      "exposure": 405810768.0,
      "mv": 313178800.0,
      "pnl": -92631968.0,
      "pnl_ratio": -0.22826394789011611
    },
    {
      "symbol": "373220",
      "name": "LG에너지솔루션",
      "side": "LONG",
      "qty": 799.0,
      "avg_price": 420000.0,
      "group": "LG에너지솔루션",
      "last_price": 373500,
      "exposure": 335580000.0,
      "mv": 298426500.0,
      "pnl": -37153500.0,
      "pnl_ratio": -0.11071428571428571
    },
    {
      "symbol": "005935",
      "name": "삼성전자우",
      "side": "LONG",
      "qty": 1600.0,
      "avg_price": 120631.0,
      "group": "삼성전자우",
      "last_price": 127900,
      "exposure": 193009600.0,
      "mv": 204640000.0,
      "pnl": 11630400.0,
      "pnl_ratio": 0.060258142600160824
    },
    {
      "symbol": "018260",
      "name": "삼성에스디에스",
      "side": "LONG",
      "qty": 1150.0,
      "avg_price": 176700.0,
      "group": "삼성에스디에스",
      "last_price": 164400,
      "exposure": 203205000.0,
      "mv": 189060000.0,
      "pnl": -14145000.0,
      "pnl_ratio": -0.06960950764006792
    }
  ],
  "total_exposure": 1995648968.0,
  "total_pnl": 1338686332.0,
  "total_pnl_ratio": 0.670802507588098
}