{
  "as_of": "2026-03-20 13:24:02",
  "currency": "KRW",
  "positions": [
    {
      "symbol": "456160",
      "name": "지투지바이오",
      "side": "LONG",
      "qty": 2680.0,
      "avg_price": 99881.0,
      "group": "지투지바이오",
      "last_price": 89600,
      "exposure": 267681080.0,
      "mv": 240128000.0,
      "pnl": -27553080.0,
      "pnl_ratio": -0.1029324896626986
    },
    {
      "symbol": "035720",
      "name": "카카오",
      "side": "LONG",
      "qty": 1580.0,
      "avg_price": 62620.0,
      "group": "카카오",
      "last_price": 50200,
      "exposure": 98939600.0,
      "mv": 79316000.0,
      "pnl": -19623600.0,
      "pnl_ratio": -0.19833918875758544
    },
    {
      "symbol": "440110",
      "name": "파두",
      "side": "LONG",
      "qty": 29000.0,
      "avg_price": 62500.0,
      "group": "파두",
      "last_price": 58600,
      "exposure": 1812500000.0,
      "mv": 1699400000.0,
      "pnl": -113100000.0,
      "pnl_ratio": -0.0624
    },
    {
      "symbol": "263750",
      "name": "펄어비스",
      "side": "LONG",
      "qty": 2000.0,
      "avg_price": 48063.0,
      "group": "펄어비스",
      "last_price": 40550,
      "exposure": 96126000.0,
      "mv": 81100000.0,
      "pnl": -15026000.0,
      "pnl_ratio": -0.15631566901774754
    },
    {
      "symbol": "003380",
      "name": "하림지주",
      "side": "LONG",
      "qty": 15000.0,
      "avg_price": 15380.0,
      "group": "하림지주",
      "last_price": 17790,
      "exposure": 230700000.0,
      "mv": 266850000.0,
      "pnl": 36150000.0,
      "pnl_ratio": 0.15669700910273082
    },
    {
      "symbol": "180640",
      "name": "한진칼",
      "side": "LONG",
      "qty": 850.0,
      "avg_price": 117771.0,
      "group": "한진칼",
      "last_price": 127600,
      "exposure": 100105350.0,
      "mv": 108460000.0,
      "pnl": 8354650.0,
      "pnl_ratio": 0.08345857638977337
    },
    {
      "symbol": "000210",
      "name": "DL",
      "side": "LONG",
      "qty": 7183.0,
      "avg_price": 56496.0,
      "group": "DL",
      "last_price": 64100,
      "exposure": 405810768.0,
      "mv": 460430300.0,
      "pnl": 54619532.0,
      "pnl_ratio": 0.13459359954687058
    },
    {
      "symbol": "373220",
      "name": "LG에너지솔루션",
      "side": "LONG",
      "qty": 799.0,
      "avg_price": 420000.0,
      "group": "LG에너지솔루션",
      "last_price": 373000,
      "exposure": 335580000.0,
      "mv": 298027000.0,
      "pnl": -37553000.0,
      "pnl_ratio": -0.11190476190476191
    },
    {
      "symbol": "005935",
      "name": "삼성전자우",
      "side": "LONG",
      "qty": 1600.0,
      "avg_price": 120631.0,
      "group": "삼성전자우",
      "last_price": 140200,
      "exposure": 193009600.0,
      "mv": 224320000.0,
      "pnl": 31310400.0,
      "pnl_ratio": 0.16222198274075486
    },
    {
      "symbol": "018260",
      "name": "삼성에스디에스",
      "side": "LONG",
      "qty": 1150.0,
      "avg_price": 176700.0,
      "group": "삼성에스디에스",
      "last_price": 162100,
      "exposure": 203205000.0,
      "mv": 186415000.0,
      "pnl": -16790000.0,
      "pnl_ratio": -0.08262591963780419
    }
  ],
  "total_exposure": 3743657398.0,
  "total_pnl": -99211098.0,
  "total_pnl_ratio": -0.026501115741254057
}