{
  "as_of": "2026-03-17 11:04:25",
  "currency": "KRW",
  "positions": [
    {
      "symbol": "456160",
      "name": "지투지바이오",
      "side": "LONG",
      "qty": 2000.0,
      "avg_price": 104932.0,
      "group": "지투지바이오",
      "last_price": 99700,
      "exposure": 209864000.0,
      "mv": 199400000.0,
      "pnl": -10464000.0,
      "pnl_ratio": -0.049860862272709944
    },
    {
      "symbol": "035720",
      "name": "카카오",
      "side": "LONG",
      "qty": 1580.0,
      "avg_price": 62620.0,
      "group": "카카오",
      "last_price": 51100,
      "exposure": 98939600.0,
      "mv": 80738000.0,
      "pnl": -18201600.0,
      "pnl_ratio": -0.18396678377515172
    },
    {
      "symbol": "440110",
      "name": "파두",
      "side": "LONG",
      "qty": 29000.0,
      "avg_price": 19120.0,
      "group": "파두",
      "last_price": 67200,
      "exposure": 554480000.0,
      "mv": 1948800000.0,
      "pnl": 1394320000.0,
      "pnl_ratio": 2.514644351464435
    },
    {
      "symbol": "003380",
      "name": "하림지주",
      "side": "LONG",
      "qty": 20000.0,
      "avg_price": 15120.0,
      "group": "하림지주",
      "last_price": 15400,
      "exposure": 302400000.0,
      "mv": 308000000.0,
      "pnl": 5600000.0,
      "pnl_ratio": 0.018518518518518517
    },
    {
      "symbol": "000210",
      "name": "DL",
      "side": "LONG",
      "qty": 7183.0,
      "avg_price": 56496.0,
      "group": "DL",
      "last_price": 45550,
      "exposure": 405810768.0,
      "mv": 327185650.0,
      "pnl": -78625118.0,
      "pnl_ratio": -0.19374822996318322
    },
    {
      "symbol": "373220",
      "name": "LG에너지솔루션",
      "side": "LONG",
      "qty": 799.0,
      "avg_price": 420000.0,
      "group": "LG에너지솔루션",
      "last_price": 372750,
      "exposure": 335580000.0,
      "mv": 297827250.0,
      "pnl": -37752750.0,
      "pnl_ratio": -0.1125
    },
    {
      "symbol": "005935",
      "name": "삼성전자우",
      "side": "LONG",
      "qty": 1600.0,
      "avg_price": 120631.0,
      "group": "삼성전자우",
      "last_price": 141450,
      "exposure": 193009600.0,
      "mv": 226320000.0,
      "pnl": 33310400.0,
      "pnl_ratio": 0.1725841616168315
    },
    {
      "symbol": "018260",
      "name": "삼성에스디에스",
      "side": "LONG",
      "qty": 1150.0,
      "avg_price": 176700.0,
      "group": "삼성에스디에스",
      "last_price": 162200,
      "exposure": 203205000.0,
      "mv": 186530000.0,
      "pnl": -16675000.0,
      "pnl_ratio": -0.08205998868138087
    }
  ],
  "total_exposure": 2303288968.0,
  "total_pnl": 1271511932.0,
  "total_pnl_ratio": 0.5520418625996736
}