{
  "as_of": "2026-03-04 09:44:41",
  "currency": "KRW",
  "positions": [
    {
      "symbol": "035720",
      "name": "카카오",
      "side": "LONG",
      "qty": 1580.0,
      "avg_price": 62620.0,
      "group": "카카오",
      "last_price": 52100,
      "exposure": 98939600.0,
      "mv": 82318000.0,
      "pnl": -16621600.0,
      "pnl_ratio": -0.1679974449057809
    },
    {
      "symbol": "440110",
      "name": "파두",
      "side": "LONG",
      "qty": 29000.0,
      "avg_price": 19120.0,
      "group": "FADU",
      "last_price": 60300,
      "exposure": 554480000.0,
      "mv": 1748700000.0,
      "pnl": 1194220000.0,
      "pnl_ratio": 2.153765690376569
    },
    {
      "symbol": "000210",
      "name": "DL",
      "side": "LONG",
      "qty": 7183.0,
      "avg_price": 56496.0,
      "group": "DL",
      "last_price": 44650,
      "exposure": 405810768.0,
      "mv": 320720950.0,
      "pnl": -85089818.0,
      "pnl_ratio": -0.20967856131407533
    },
    {
      "symbol": "373220",
      "name": "LG에너지솔루션",
      "side": "LONG",
      "qty": 710.0,
      "avg_price": 423058.0,
      "group": "LG에너지솔루션",
      "last_price": 378500,
      "exposure": 300371180.0,
      "mv": 268735000.0,
      "pnl": -31636180.0,
      "pnl_ratio": -0.1053236199291823
    },
    {
      "symbol": "018260",
      "name": "삼성SDS",
      "side": "LONG",
      "qty": 1150.0,
      "avg_price": 176700.0,
      "group": "SAMSUNG SDS",
      "last_price": 170200,
      "exposure": 203205000.0,
      "mv": 195730000.0,
      "pnl": -7475000.0,
      "pnl_ratio": -0.03678551216751556
    }
  ],
  "total_exposure": 1562806548.0,
  "total_pnl": 1053397402.0,
  "total_pnl_ratio": 0.6740420964757821
}