{
  "as_of": "2026-02-13 12:40:40",
  "currency": "KRW",
  "positions": [
    {
      "symbol": "440110",
      "name": "파두",
      "side": "LONG",
      "qty": 29000.0,
      "avg_price": 19120.0,
      "group": "FADU",
      "last_price": 53900,
      "exposure": 554480000.0,
      "mv": 1563100000.0,
      "pnl": 1008620000.0,
      "pnl_ratio": 1.8190376569037656
    },
    {
      "symbol": "229200",
      "name": "KODEX 코스닥150",
      "side": "LONG",
      "qty": 26000.0,
      "avg_price": 19000.0,
      "group": "229200",
      "last_price": 18985,
      "exposure": 494000000.0,
      "mv": 493610000.0,
      "pnl": -390000.0,
      "pnl_ratio": -0.0007894736842105263
    },
    {
      "symbol": "057050",
      "name": "현대홈쇼핑",
      "side": "LONG",
      "qty": 3750.0,
      "avg_price": 65702.0,
      "group": "057050",
      "last_price": 76500,
      "exposure": 246382500.0,
      "mv": 286875000.0,
      "pnl": 40492500.0,
      "pnl_ratio": 0.1643481172567045
    },
    {
      "symbol": "005440",
      "name": "현대지에프홀딩스",
      "side": "LONG",
      "qty": 23270.0,
      "avg_price": 10909.0,
      "group": "005440",
      "last_price": 13940,
      "exposure": 253852430.0,
      "mv": 324383800.0,
      "pnl": 70531370.0,
      "pnl_ratio": 0.2778439820331836
    },
    {
      "symbol": "033240",
      "name": "자화전자",
      "side": "LONG",
      "qty": 3700.0,
      "avg_price": 40171.0,
      "group": "033240",
      "last_price": 41600,
      "exposure": 148632700.0,
      "mv": 153920000.0,
      "pnl": 5287300.0,
      "pnl_ratio": 0.03557292574245102
    },
    {
      "symbol": "034020",
      "name": "두산에너빌리티",
      "side": "LONG",
      "qty": 2620.0,
      "avg_price": 94501.0,
      "group": "034020",
      "last_price": 99600,
      "exposure": 247592620.0,
      "mv": 260952000.0,
      "pnl": 13359380.0,
      "pnl_ratio": 0.05395710098305838
    },
    {
      "symbol": "112610",
      "name": "씨에스윈드",
      "side": "LONG",
      "qty": 3230.0,
      "avg_price": 44308.0,
      "group": "112610",
      "last_price": 43200,
      "exposure": 143114840.0,
      "mv": 139536000.0,
      "pnl": -3578840.0,
      "pnl_ratio": -0.025006770786313984
    },
    {
      "symbol": "180640",
      "name": "한진칼",
      "side": "LONG",
      "qty": 5000.0,
      "avg_price": 115000.0,
      "group": "한진칼",
      "last_price": 133200,
      "exposure": 575000000.0,
      "mv": 666000000.0,
      "pnl": 91000000.0,
      "pnl_ratio": 0.1582608695652174
    },
    {
      "symbol": "000210",
      "name": "DL",
      "side": "LONG",
      "qty": 7183.0,
      "avg_price": 56496.0,
      "group": "DL",
      "last_price": 48100,
      "exposure": 405810768.0,
      "mv": 345502300.0,
      "pnl": -60308468.0,
      "pnl_ratio": -0.14861229113565563
    },
    {
      "symbol": "018260",
      "name": "삼성SDS",
      "side": "LONG",
      "qty": 1150.0,
      "avg_price": 176700.0,
      "group": "SAMSUNG SDS",
      "last_price": 170600,
      "exposure": 203205000.0,
      "mv": 196190000.0,
      "pnl": -7015000.0,
      "pnl_ratio": -0.0345217883418223
    }
  ],
  "total_exposure": 3272070858.0,
  "total_pnl": 1157998242.0,
  "total_pnl_ratio": 0.35390377906052056
}