{
  "as_of": "2026-03-25 09:19:13",
  "currency": "KRW",
  "positions": [
    {
      "symbol": "456160",
      "name": "지투지바이오",
      "side": "LONG",
      "qty": 2680.0,
      "avg_price": 99881.0,
      "group": "지투지바이오",
      "last_price": 75300,
      "exposure": 267681080.0,
      "mv": 201804000.0,
      "pnl": -65877080.0,
      "pnl_ratio": -0.24610286240626345
    },
    {
      "symbol": "035720",
      "name": "카카오",
      "side": "LONG",
      "qty": 1580.0,
      "avg_price": 62620.0,
      "group": "카카오",
      "last_price": 49650,
      "exposure": 98939600.0,
      "mv": 78447000.0,
      "pnl": -20492600.0,
      "pnl_ratio": -0.2071223251357394
    },
    {
      "symbol": "440110",
      "name": "파두",
      "side": "LONG",
      "qty": 29000.0,
      "avg_price": 62500.0,
      "group": "파두",
      "last_price": 57700,
      "exposure": 1812500000.0,
      "mv": 1673300000.0,
      "pnl": -139200000.0,
      "pnl_ratio": -0.0768
    },
    {
      "symbol": "263750",
      "name": "펄어비스",
      "side": "LONG",
      "qty": 2000.0,
      "avg_price": 48063.0,
      "group": "펄어비스",
      "last_price": 46250,
      "exposure": 96126000.0,
      "mv": 92500000.0,
      "pnl": -3626000.0,
      "pnl_ratio": -0.037721324095458045
    },
    {
      "symbol": "003380",
      "name": "하림지주",
      "side": "LONG",
      "qty": 20000.0,
      "avg_price": 15450.0,
      "group": "하림지주",
      "last_price": 15680,
      "exposure": 309000000.0,
      "mv": 313600000.0,
      "pnl": 4600000.0,
      "pnl_ratio": 0.01488673139158576
    },
    {
      "symbol": "180640",
      "name": "한진칼",
      "side": "LONG",
      "qty": 1700.0,
      "avg_price": 118759.0,
      "group": "한진칼",
      "last_price": 128500,
      "exposure": 201890300.0,
      "mv": 218450000.0,
      "pnl": 16559700.0,
      "pnl_ratio": 0.08202325718471863
    },
    {
      "symbol": "229200",
      "name": "KODEX코스닥150",
      "side": "LONG",
      "qty": 312.0,
      "avg_price": 19250.0,
      "group": "KODEX코스닥150",
      "last_price": 19800,
      "exposure": 6006000.0,
      "mv": 6177600.0,
      "pnl": 171600.0,
      "pnl_ratio": 0.02857142857142857
    },
    {
      "symbol": "373220",
      "name": "LG에너지솔루션",
      "side": "LONG",
      "qty": 949.0,
      "avg_price": 412503.0,
      "group": "LG에너지솔루션",
      "last_price": 393500,
      "exposure": 391465347.0,
      "mv": 373431500.0,
      "pnl": -18033847.0,
      "pnl_ratio": -0.04606754375119696
    },
    {
      "symbol": "005935",
      "name": "삼성전자우",
      "side": "LONG",
      "qty": 1600.0,
      "avg_price": 120631.0,
      "group": "삼성전자우",
      "last_price": 138000,
      "exposure": 193009600.0,
      "mv": 220800000.0,
      "pnl": 27790400.0,
      "pnl_ratio": 0.14398454791886
    },
    {
      "symbol": "018260",
      "name": "삼성에스디에스",
      "side": "LONG",
      "qty": 1150.0,
      "avg_price": 176700.0,
      "group": "삼성에스디에스",
      "last_price": 160300,
      "exposure": 203205000.0,
      "mv": 184345000.0,
      "pnl": -18860000.0,
      "pnl_ratio": -0.09281267685342388
    }
  ],
  "total_exposure": 3579822927.0,
  "total_pnl": -216967827.0,
  "total_pnl_ratio": -0.060608536071315014,
  "usd_krw": 1488.075435,
  "wti": 88.55000305175781
}