{
  "as_of": "2026-02-20 11:36:54",
  "currency": "KRW",
  "positions": [
    {
      "symbol": "440110",
      "name": "파두",
      "side": "LONG",
      "qty": 29000.0,
      "avg_price": 19120.0,
      "group": "FADU",
      "last_price": 51900,
      "exposure": 554480000.0,
      "mv": 1505100000.0,
      "pnl": 950620000.0,
      "pnl_ratio": 1.7144351464435146
    },
    {
      "symbol": "229200",
      "name": "KODEX 코스닥150",
      "side": "LONG",
      "qty": 26000.0,
      "avg_price": 19000.0,
      "group": "229200",
      "last_price": 20255,
      "exposure": 494000000.0,
      "mv": 526630000.0,
      "pnl": 32630000.0,
      "pnl_ratio": 0.06605263157894736
    },
    {
      "symbol": "033240",
      "name": "자화전자",
      "side": "LONG",
      "qty": 3700.0,
      "avg_price": 40171.0,
      "group": "033240",
      "last_price": 42500,
      "exposure": 148632700.0,
      "mv": 157250000.0,
      "pnl": 8617300.0,
      "pnl_ratio": 0.057977147693609815
    },
    {
      "symbol": "034020",
      "name": "두산에너빌리티",
      "side": "LONG",
      "qty": 3120.0,
      "avg_price": 94820.0,
      "group": "034020",
      "last_price": 104000,
      "exposure": 295838400.0,
      "mv": 324480000.0,
      "pnl": 28641600.0,
      "pnl_ratio": 0.09681501792870702
    },
    {
      "symbol": "180640",
      "name": "한진칼",
      "side": "LONG",
      "qty": 5000.0,
      "avg_price": 115000.0,
      "group": "한진칼",
      "last_price": 145900,
      "exposure": 575000000.0,
      "mv": 729500000.0,
      "pnl": 154500000.0,
      "pnl_ratio": 0.26869565217391306
    },
    {
      "symbol": "000210",
      "name": "DL",
      "side": "LONG",
      "qty": 7183.0,
      "avg_price": 56496.0,
      "group": "DL",
      "last_price": 49400,
      "exposure": 405810768.0,
      "mv": 354840200.0,
      "pnl": -50970568.0,
      "pnl_ratio": -0.12560181251770036
    },
    {
      "symbol": "018260",
      "name": "삼성SDS",
      "side": "LONG",
      "qty": 1150.0,
      "avg_price": 176700.0,
      "group": "SAMSUNG SDS",
      "last_price": 173000,
      "exposure": 203205000.0,
      "mv": 198950000.0,
      "pnl": -4255000.0,
      "pnl_ratio": -0.020939445387662705
    }
  ],
  "total_exposure": 2676966868.0,
  "total_pnl": 1119783332.0,
  "total_pnl_ratio": 0.41830302249373974
}