{
  "as_of": "2026-03-25 12:06:56",
  "currency": "KRW",
  "positions": [
    {
      "symbol": "456160",
      "name": "지투지바이오",
      "side": "LONG",
      "qty": 2680.0,
      "avg_price": 99881.0,
      "group": "지투지바이오",
      "last_price": 74200,
      "exposure": 267681080.0,
      "mv": 198856000.0,
      "pnl": -68825080.0,
      "pnl_ratio": -0.25711596800192227
    },
    {
      "symbol": "035720",
      "name": "카카오",
      "side": "LONG",
      "qty": 1580.0,
      "avg_price": 62620.0,
      "group": "카카오",
      "last_price": 49200,
      "exposure": 98939600.0,
      "mv": 77736000.0,
      "pnl": -21203600.0,
      "pnl_ratio": -0.21430852762695624
    },
    {
      "symbol": "440110",
      "name": "파두",
      "side": "LONG",
      "qty": 29000.0,
      "avg_price": 62500.0,
      "group": "파두",
      "last_price": 56700,
      "exposure": 1812500000.0,
      "mv": 1644300000.0,
      "pnl": -168200000.0,
      "pnl_ratio": -0.0928
    },
    {
      "symbol": "263750",
      "name": "펄어비스",
      "side": "LONG",
      "qty": 4300.0,
      "avg_price": 47744.0,
      "group": "펄어비스",
      "last_price": 51000,
      "exposure": 205299200.0,
      "mv": 219300000.0,
      "pnl": 14000800.0,
      "pnl_ratio": 0.0681970509383378
    },
    {
      "symbol": "003380",
      "name": "하림지주",
      "side": "LONG",
      "qty": 20000.0,
      "avg_price": 15450.0,
      "group": "하림지주",
      "last_price": 15310,
      "exposure": 309000000.0,
      "mv": 306200000.0,
      "pnl": -2800000.0,
      "pnl_ratio": -0.009061488673139158
    },
    {
      "symbol": "180640",
      "name": "한진칼",
      "side": "LONG",
      "qty": 1700.0,
      "avg_price": 118759.0,
      "group": "한진칼",
      "last_price": 124900,
      "exposure": 201890300.0,
      "mv": 212330000.0,
      "pnl": 10439700.0,
      "pnl_ratio": 0.05170976515464091
    },
    {
      "symbol": "229200",
      "name": "KODEX코스닥150",
      "side": "LONG",
      "qty": 312.0,
      "avg_price": 19250.0,
      "group": "KODEX코스닥150",
      "last_price": 19920,
      "exposure": 6006000.0,
      "mv": 6215040.0,
      "pnl": 209040.0,
      "pnl_ratio": 0.034805194805194804
    },
    {
      "symbol": "373220",
      "name": "LG에너지솔루션",
      "side": "LONG",
      "qty": 949.0,
      "avg_price": 412503.0,
      "group": "LG에너지솔루션",
      "last_price": 388500,
      "exposure": 391465347.0,
      "mv": 368686500.0,
      "pnl": -22778847.0,
      "pnl_ratio": -0.05818866771878023
    },
    {
      "symbol": "005935",
      "name": "삼성전자우",
      "side": "LONG",
      "qty": 1600.0,
      "avg_price": 120631.0,
      "group": "삼성전자우",
      "last_price": 136000,
      "exposure": 193009600.0,
      "mv": 217600000.0,
      "pnl": 24590400.0,
      "pnl_ratio": 0.1274050617171374
    },
    {
      "symbol": "018260",
      "name": "삼성에스디에스",
      "side": "LONG",
      "qty": 1150.0,
      "avg_price": 176700.0,
      "group": "삼성에스디에스",
      "last_price": 158000,
      "exposure": 203205000.0,
      "mv": 181700000.0,
      "pnl": -21505000.0,
      "pnl_ratio": -0.10582908885116016
    }
  ],
  "total_exposure": 3688996127.0,
  "total_pnl": -256072587.0,
  "total_pnl_ratio": -0.06941524961920893,
  "usd_krw": 1497.971258,
  "wti": null
}