{
  "as_of": "2026-03-31 09:45:02",
  "currency": "KRW",
  "positions": [
    {
      "symbol": "456160",
      "name": "지투지바이오",
      "side": "LONG",
      "qty": 2680.0,
      "avg_price": 99881.0,
      "group": "지투지바이오",
      "last_price": 68000,
      "exposure": 267681080.0,
      "mv": 182240000.0,
      "pnl": -85441080.0,
      "pnl_ratio": -0.3191898359047266
    },
    {
      "symbol": "035720",
      "name": "카카오",
      "side": "LONG",
      "qty": 1580.0,
      "avg_price": 62620.0,
      "group": "카카오",
      "last_price": 46000,
      "exposure": 98939600.0,
      "mv": 72680000.0,
      "pnl": -26259600.0,
      "pnl_ratio": -0.26541041200894283
    },
    {
      "symbol": "440110",
      "name": "파두",
      "side": "LONG",
      "qty": 29000.0,
      "avg_price": 62500.0,
      "group": "파두",
      "last_price": 47550,
      "exposure": 1812500000.0,
      "mv": 1378950000.0,
      "pnl": -433550000.0,
      "pnl_ratio": -0.2392
    },
    {
      "symbol": "263750",
      "name": "펄어비스",
      "side": "LONG",
      "qty": 6600.0,
      "avg_price": 47648.0,
      "group": "펄어비스",
      "last_price": 69200,
      "exposure": 314476800.0,
      "mv": 456720000.0,
      "pnl": 142243200.0,
      "pnl_ratio": 0.45231699126930824
    },
    {
      "symbol": "003380",
      "name": "하림지주",
      "side": "LONG",
      "qty": 20000.0,
      "avg_price": 15450.0,
      "group": "하림지주",
      "last_price": 13660,
      "exposure": 309000000.0,
      "mv": 273200000.0,
      "pnl": -35800000.0,
      "pnl_ratio": -0.11585760517799353
    },
    {
      "symbol": "180640",
      "name": "한진칼",
      "side": "LONG",
      "qty": 2500.0,
      "avg_price": 119193.0,
      "group": "한진칼",
      "last_price": 108100,
      "exposure": 297982500.0,
      "mv": 270250000.0,
      "pnl": -27732500.0,
      "pnl_ratio": -0.09306754591293113
    },
    {
      "symbol": "229200",
      "name": "KODEX코스닥150",
      "side": "LONG",
      "qty": 312.0,
      "avg_price": 19250.0,
      "group": "KODEX코스닥150",
      "last_price": 18745,
      "exposure": 6006000.0,
      "mv": 5848440.0,
      "pnl": -157560.0,
      "pnl_ratio": -0.026233766233766234
    },
    {
      "symbol": "373220",
      "name": "LG에너지솔루션",
      "side": "LONG",
      "qty": 949.0,
      "avg_price": 412503.0,
      "group": "LG에너지솔루션",
      "last_price": 401500,
      "exposure": 391465347.0,
      "mv": 381023500.0,
      "pnl": -10441847.0,
      "pnl_ratio": -0.026673745403063734
    },
    {
      "symbol": "005935",
      "name": "삼성전자우",
      "side": "LONG",
      "qty": 1600.0,
      "avg_price": 120631.0,
      "group": "삼성전자우",
      "last_price": 115400,
      "exposure": 193009600.0,
      "mv": 184640000.0,
      "pnl": -8369600.0,
      "pnl_ratio": -0.043363646160605486
    },
    {
      "symbol": "018260",
      "name": "삼성에스디에스",
      "side": "LONG",
      "qty": 1150.0,
      "avg_price": 176700.0,
      "group": "삼성에스디에스",
      "last_price": 152100,
      "exposure": 203205000.0,
      "mv": 174915000.0,
      "pnl": -28290000.0,
      "pnl_ratio": -0.13921901528013583
    }
  ],
  "total_exposure": 3894265927.0,
  "total_pnl": -513798987.0,
  "total_pnl_ratio": -0.1319373141514791,
  "usd_krw": 1516.151895,
  "wti": 106.30000305175781
}