{
  "as_of": "2026-05-12 09:53:45",
  "currency": "KRW",
  "positions": [
    {
      "symbol": "456160",
      "name": "지투지바이오",
      "side": "LONG",
      "qty": 2680.0,
      "avg_price": 99881.0,
      "group": "지투지바이오",
      "last_price": 73500.0,
      "exposure": 267681080.0,
      "mv": 196980000.0,
      "pnl": -70701080.0,
      "pnl_ratio": -0.26412430792643243
    },
    {
      "symbol": "035720",
      "name": "카카오",
      "side": "LONG",
      "qty": 1580.0,
      "avg_price": 62620.0,
      "group": "카카오",
      "last_price": 44300.0,
      "exposure": 98939600.0,
      "mv": 69994000.0,
      "pnl": -28945600.0,
      "pnl_ratio": -0.29255828808687323
    },
    {
      "symbol": "440110",
      "name": "파두",
      "side": "LONG",
      "qty": 29000.0,
      "avg_price": 62500.0,
      "group": "파두",
      "last_price": 99100.0,
      "exposure": 1812500000.0,
      "mv": 2873900000.0,
      "pnl": 1061400000.0,
      "pnl_ratio": 0.5856
    },
    {
      "symbol": "440110",
      "name": "파두[S]",
      "side": "LONG",
      "qty": 6761.0,
      "avg_price": 11756.0,
      "group": "파두[S]",
      "last_price": 99100.0,
      "exposure": 79482316.0,
      "mv": 670015100.0,
      "pnl": 590532784.0,
      "pnl_ratio": 7.429738006124532
    },
    {
      "symbol": "263750",
      "name": "펄어비스",
      "side": "LONG",
      "qty": 7147.0,
      "avg_price": 56599.0,
      "group": "펄어비스",
      "last_price": 53100.0,
      "exposure": 404513053.0,
      "mv": 379505700.0,
      "pnl": -25007353.0,
      "pnl_ratio": -0.06182088022756586
    },
    {
      "symbol": "003380",
      "name": "하림지주",
      "side": "LONG",
      "qty": 20000.0,
      "avg_price": 15450.0,
      "group": "하림지주",
      "last_price": 12210.0,
      "exposure": 309000000.0,
      "mv": 244200000.0,
      "pnl": -64800000.0,
      "pnl_ratio": -0.20970873786407768
    },
    {
      "symbol": "352820",
      "name": "하이브",
      "side": "LONG",
      "qty": 740.0,
      "avg_price": 268520.0,
      "group": "하이브",
      "last_price": 235000.0,
      "exposure": 198704800.0,
      "mv": 173900000.0,
      "pnl": -24804800.0,
      "pnl_ratio": -0.1248324147177119
    },
    {
      "symbol": "180640",
      "name": "한진칼",
      "side": "LONG",
      "qty": 3431.0,
      "avg_price": 117528.0,
      "group": "한진칼",
      "last_price": 110700.0,
      "exposure": 403238568.0,
      "mv": 379811700.0,
      "pnl": -23426868.0,
      "pnl_ratio": -0.05809679395548295
    },
    {
      "symbol": "005935",
      "name": "삼성전자우",
      "side": "LONG",
      "qty": 2480.0,
      "avg_price": 118794.0,
      "group": "삼성전자우",
      "last_price": 193500.0,
      "exposure": 294609120.0,
      "mv": 479880000.0,
      "pnl": 185270880.0,
      "pnl_ratio": 0.628870144956816
    },
    {
      "symbol": "018260",
      "name": "삼성에스디에스",
      "side": "LONG",
      "qty": 1150.0,
      "avg_price": 176700.0,
      "group": "삼성에스디에스",
      "last_price": 182600.0,
      "exposure": 203205000.0,
      "mv": 209990000.0,
      "pnl": 6785000.0,
      "pnl_ratio": 0.03338992642897567
    },
    {
      "symbol": "004020",
      "name": "현대제철",
      "side": "LONG",
      "qty": 2260.0,
      "avg_price": 43620.0,
      "group": "현대제철",
      "last_price": 45150.0,
      "exposure": 98581200.0,
      "mv": 102039000.0,
      "pnl": 3457800.0,
      "pnl_ratio": 0.035075653370013754
    },
    {
      "symbol": "011210",
      "name": "현대위아",
      "side": "LONG",
      "qty": 1120.0,
      "avg_price": 89345.0,
      "group": "현대위아",
      "last_price": 95500.0,
      "exposure": 100066400.0,
      "mv": 106960000.0,
      "pnl": 6893600.0,
      "pnl_ratio": 0.0688902568694387
    },
    {
      "symbol": "373220",
      "name": "LG에너지솔루션",
      "side": "LONG",
      "qty": 430.0,
      "avg_price": 468352.0,
      "group": "LG에너지솔루션",
      "last_price": 463000.0,
      "exposure": 201391360.0,
      "mv": 199090000.0,
      "pnl": -2301360.0,
      "pnl_ratio": -0.011427302541678053
    }
  ],
  "total_exposure": 4471912497.0,
  "total_pnl": 1614353003.0,
  "total_pnl_ratio": 0.3609983433448206,
  "usd_krw": 1473.051627,
  "wti": 98.6500015258789
}