{
  "as_of": "2026-03-20 09:10:19",
  "currency": "KRW",
  "positions": [
    {
      "symbol": "456160",
      "name": "지투지바이오",
      "side": "LONG",
      "qty": 2680.0,
      "avg_price": 99881.0,
      "group": "지투지바이오",
      "last_price": 88200,
      "exposure": 267681080.0,
      "mv": 236376000.0,
      "pnl": -31305080.0,
      "pnl_ratio": -0.11694916951171895
    },
    {
      "symbol": "035720",
      "name": "카카오",
      "side": "LONG",
      "qty": 1580.0,
      "avg_price": 62620.0,
      "group": "카카오",
      "last_price": 50100,
      "exposure": 98939600.0,
      "mv": 79158000.0,
      "pnl": -19781600.0,
      "pnl_ratio": -0.1999361226445225
    },
    {
      "symbol": "440110",
      "name": "파두",
      "side": "LONG",
      "qty": 29000.0,
      "avg_price": 62500.0,
      "group": "파두",
      "last_price": 56800,
      "exposure": 1812500000.0,
      "mv": 1647200000.0,
      "pnl": -165300000.0,
      "pnl_ratio": -0.0912
    },
    {
      "symbol": "263750",
      "name": "펄어비스",
      "side": "LONG",
      "qty": 2000.0,
      "avg_price": 48063.0,
      "group": "펄어비스",
      "last_price": 44000,
      "exposure": 96126000.0,
      "mv": 88000000.0,
      "pnl": -8126000.0,
      "pnl_ratio": -0.08453488130162495
    },
    {
      "symbol": "003380",
      "name": "하림지주",
      "side": "LONG",
      "qty": 30000.0,
      "avg_price": 15380.0,
      "group": "하림지주",
      "last_price": 16200,
      "exposure": 461400000.0,
      "mv": 486000000.0,
      "pnl": 24600000.0,
      "pnl_ratio": 0.053315994798439535
    },
    {
      "symbol": "180640",
      "name": "한진칼",
      "side": "LONG",
      "qty": 850.0,
      "avg_price": 117771.0,
      "group": "한진칼",
      "last_price": 127400,
      "exposure": 100105350.0,
      "mv": 108290000.0,
      "pnl": 8184650.0,
      "pnl_ratio": 0.08176036545499317
    },
    {
      "symbol": "000210",
      "name": "DL",
      "side": "LONG",
      "qty": 7183.0,
      "avg_price": 56496.0,
      "group": "DL",
      "last_price": 60800,
      "exposure": 405810768.0,
      "mv": 436726400.0,
      "pnl": 30915632.0,
      "pnl_ratio": 0.07618238459359955
    },
    {
      "symbol": "373220",
      "name": "LG에너지솔루션",
      "side": "LONG",
      "qty": 799.0,
      "avg_price": 420000.0,
      "group": "LG에너지솔루션",
      "last_price": 376000,
      "exposure": 335580000.0,
      "mv": 300424000.0,
      "pnl": -35156000.0,
      "pnl_ratio": -0.10476190476190476
    },
    {
      "symbol": "005935",
      "name": "삼성전자우",
      "side": "LONG",
      "qty": 1600.0,
      "avg_price": 120631.0,
      "group": "삼성전자우",
      "last_price": 143000,
      "exposure": 193009600.0,
      "mv": 228800000.0,
      "pnl": 35790400.0,
      "pnl_ratio": 0.18543326342316652
    },
    {
      "symbol": "018260",
      "name": "삼성에스디에스",
      "side": "LONG",
      "qty": 1150.0,
      "avg_price": 176700.0,
      "group": "삼성에스디에스",
      "last_price": 163300,
      "exposure": 203205000.0,
      "mv": 187795000.0,
      "pnl": -15410000.0,
      "pnl_ratio": -0.07583474816072439
    }
  ],
  "total_exposure": 3974357398.0,
  "total_pnl": -175587998.0,
  "total_pnl_ratio": -0.044180223471688894
}