{
  "as_of": "2026-03-04 13:19:32",
  "currency": "KRW",
  "positions": [
    {
      "symbol": "033240",
      "name": "자화전자",
      "side": "LONG",
      "qty": 1430.0,
      "avg_price": 35000.0,
      "group": "자화전자",
      "last_price": 33400,
      "exposure": 50050000.0,
      "mv": 47762000.0,
      "pnl": -2288000.0,
      "pnl_ratio": -0.045714285714285714
    },
    {
      "symbol": "035720",
      "name": "카카오",
      "side": "LONG",
      "qty": 1580.0,
      "avg_price": 62620.0,
      "group": "카카오",
      "last_price": 49250,
      "exposure": 98939600.0,
      "mv": 77815000.0,
      "pnl": -21124600.0,
      "pnl_ratio": -0.2135100606834877
    },
    {
      "symbol": "440110",
      "name": "파두",
      "side": "LONG",
      "qty": 29000.0,
      "avg_price": 19120.0,
      "group": "파두",
      "last_price": 58200,
      "exposure": 554480000.0,
      "mv": 1687800000.0,
      "pnl": 1133320000.0,
      "pnl_ratio": 2.0439330543933054
    },
    {
      "symbol": "180640",
      "name": "한진칼",
      "side": "LONG",
      "qty": 830.0,
      "avg_price": 120000.0,
      "group": "한진칼",
      "last_price": 116100,
      "exposure": 99600000.0,
      "mv": 96363000.0,
      "pnl": -3237000.0,
      "pnl_ratio": -0.0325
    },
    {
      "symbol": "000210",
      "name": "DL",
      "side": "LONG",
      "qty": 7183.0,
      "avg_price": 56496.0,
      "group": "DL",
      "last_price": 42550,
      "exposure": 405810768.0,
      "mv": 305636650.0,
      "pnl": -100174118.0,
      "pnl_ratio": -0.2468493344661569
    },
    {
      "symbol": "373220",
      "name": "LG에너지솔루션",
      "side": "LONG",
      "qty": 710.0,
      "avg_price": 423058.0,
      "group": "LG에너지솔루션",
      "last_price": 361500,
      "exposure": 300371180.0,
      "mv": 256665000.0,
      "pnl": -43706180.0,
      "pnl_ratio": -0.14550723541452945
    },
    {
      "symbol": "005935",
      "name": "삼성전자우",
      "side": "LONG",
      "qty": 800.0,
      "avg_price": 124412.0,
      "group": "삼성전자우",
      "last_price": 119100,
      "exposure": 99529600.0,
      "mv": 95280000.0,
      "pnl": -4249600.0,
      "pnl_ratio": -0.04269684596341189
    },
    {
      "symbol": "018260",
      "name": "삼성에스디에스",
      "side": "LONG",
      "qty": 1150.0,
      "avg_price": 176700.0,
      "group": "삼성에스디에스",
      "last_price": 161200,
      "exposure": 203205000.0,
      "mv": 185380000.0,
      "pnl": -17825000.0,
      "pnl_ratio": -0.08771929824561403
    }
  ],
  "total_exposure": 1811986148.0,
  "total_pnl": 940715502.0,
  "total_pnl_ratio": 0.5191626343492335
}