{
  "as_of": "2026-04-09 13:20:55",
  "currency": "KRW",
  "positions": [
    {
      "symbol": "456160",
      "name": "지투지바이오",
      "side": "LONG",
      "qty": 2680.0,
      "avg_price": 99881.0,
      "group": "지투지바이오",
      "last_price": 71300,
      "exposure": 267681080.0,
      "mv": 191084000.0,
      "pnl": -76597080.0,
      "pnl_ratio": -0.28615051911775014
    },
    {
      "symbol": "035720",
      "name": "카카오",
      "side": "LONG",
      "qty": 1580.0,
      "avg_price": 62620.0,
      "group": "카카오",
      "last_price": 47150,
      "exposure": 98939600.0,
      "mv": 74497000.0,
      "pnl": -24442600.0,
      "pnl_ratio": -0.2470456723091664
    },
    {
      "symbol": "440110",
      "name": "파두",
      "side": "LONG",
      "qty": 29000.0,
      "avg_price": 62500.0,
      "group": "파두",
      "last_price": 55100,
      "exposure": 1812500000.0,
      "mv": 1597900000.0,
      "pnl": -214600000.0,
      "pnl_ratio": -0.1184
    },
    {
      "symbol": "263750",
      "name": "펄어비스",
      "side": "LONG",
      "qty": 1720.0,
      "avg_price": 57882.0,
      "group": "펄어비스",
      "last_price": 56500,
      "exposure": 99557040.0,
      "mv": 97180000.0,
      "pnl": -2377040.0,
      "pnl_ratio": -0.023876161846515323
    },
    {
      "symbol": "003380",
      "name": "하림지주",
      "side": "LONG",
      "qty": 20000.0,
      "avg_price": 15450.0,
      "group": "하림지주",
      "last_price": 13330,
      "exposure": 309000000.0,
      "mv": 266600000.0,
      "pnl": -42400000.0,
      "pnl_ratio": -0.1372168284789644
    },
    {
      "symbol": "180640",
      "name": "한진칼",
      "side": "LONG",
      "qty": 2921.0,
      "avg_price": 117850.0,
      "group": "한진칼",
      "last_price": 109600,
      "exposure": 344239850.0,
      "mv": 320141600.0,
      "pnl": -24098250.0,
      "pnl_ratio": -0.07000424268137463
    },
    {
      "symbol": "229200",
      "name": "KODEX코스닥150",
      "side": "LONG",
      "qty": 16436.0,
      "avg_price": 18685.0,
      "group": "KODEX코스닥150",
      "last_price": 18345,
      "exposure": 307106660.0,
      "mv": 301518420.0,
      "pnl": -5588240.0,
      "pnl_ratio": -0.018196414236018196
    },
    {
      "symbol": "373220",
      "name": "LG에너지솔루션",
      "side": "LONG",
      "qty": 949.0,
      "avg_price": 412503.0,
      "group": "LG에너지솔루션",
      "last_price": 418500,
      "exposure": 391465347.0,
      "mv": 397156500.0,
      "pnl": 5691153.0,
      "pnl_ratio": 0.01453807608671937
    },
    {
      "symbol": "005935",
      "name": "삼성전자우",
      "side": "LONG",
      "qty": 2480.0,
      "avg_price": 118794.0,
      "group": "삼성전자우",
      "last_price": 137200,
      "exposure": 294609120.0,
      "mv": 340256000.0,
      "pnl": 45646880.0,
      "pnl_ratio": 0.15494048520969073
    },
    {
      "symbol": "018260",
      "name": "삼성에스디에스",
      "side": "LONG",
      "qty": 1150.0,
      "avg_price": 176700.0,
      "group": "삼성에스디에스",
      "last_price": 149900,
      "exposure": 203205000.0,
      "mv": 172385000.0,
      "pnl": -30820000.0,
      "pnl_ratio": -0.15166949632144877
    }
  ],
  "total_exposure": 4128303697.0,
  "total_pnl": -369585177.0,
  "total_pnl_ratio": -0.08952470654437902,
  "usd_krw": 1478.049509,
  "wti": 97.30000305175781
}