{
  "as_of": "2026-05-08 11:39:40",
  "currency": "KRW",
  "positions": [
    {
      "symbol": "456160",
      "name": "지투지바이오",
      "side": "LONG",
      "qty": 2680.0,
      "avg_price": 99881.0,
      "group": "지투지바이오",
      "last_price": 80200,
      "exposure": 267681080.0,
      "mv": 214936000.0,
      "pnl": -52745080.0,
      "pnl_ratio": -0.1970444829346923
    },
    {
      "symbol": "035720",
      "name": "카카오",
      "side": "LONG",
      "qty": 1580.0,
      "avg_price": 62620.0,
      "group": "카카오",
      "last_price": 46850,
      "exposure": 98939600.0,
      "mv": 74023000.0,
      "pnl": -24916600.0,
      "pnl_ratio": -0.25183647396997766
    },
    {
      "symbol": "440110",
      "name": "파두",
      "side": "LONG",
      "qty": 29000.0,
      "avg_price": 62500.0,
      "group": "파두",
      "last_price": 91100,
      "exposure": 1812500000.0,
      "mv": 2641900000.0,
      "pnl": 829400000.0,
      "pnl_ratio": 0.4576
    },
    {
      "symbol": "440110",
      "name": "파두[S]",
      "side": "LONG",
      "qty": 17061.0,
      "avg_price": 11756.0,
      "group": "파두[S]",
      "last_price": 91100,
      "exposure": 200569116.0,
      "mv": 1554257100.0,
      "pnl": 1353687984.0,
      "pnl_ratio": 6.749234433480776
    },
    {
      "symbol": "263750",
      "name": "펄어비스",
      "side": "LONG",
      "qty": 7147.0,
      "avg_price": 56599.0,
      "group": "펄어비스",
      "last_price": 52500,
      "exposure": 404513053.0,
      "mv": 375217500.0,
      "pnl": -29295553.0,
      "pnl_ratio": -0.07242177423629392
    },
    {
      "symbol": "003380",
      "name": "하림지주",
      "side": "LONG",
      "qty": 20000.0,
      "avg_price": 15450.0,
      "group": "하림지주",
      "last_price": 12620,
      "exposure": 309000000.0,
      "mv": 252400000.0,
      "pnl": -56600000.0,
      "pnl_ratio": -0.1831715210355987
    },
    {
      "symbol": "352820",
      "name": "하이브",
      "side": "LONG",
      "qty": 740.0,
      "avg_price": 268520.0,
      "group": "하이브",
      "last_price": 248500,
      "exposure": 198704800.0,
      "mv": 183890000.0,
      "pnl": -14814800.0,
      "pnl_ratio": -0.07455683003128259
    },
    {
      "symbol": "180640",
      "name": "한진칼",
      "side": "LONG",
      "qty": 3431.0,
      "avg_price": 117528.0,
      "group": "한진칼",
      "last_price": 114700,
      "exposure": 403238568.0,
      "mv": 393535700.0,
      "pnl": -9702868.0,
      "pnl_ratio": -0.024062351099312505
    },
    {
      "symbol": "005935",
      "name": "삼성전자우",
      "side": "LONG",
      "qty": 2480.0,
      "avg_price": 118794.0,
      "group": "삼성전자우",
      "last_price": 177800,
      "exposure": 294609120.0,
      "mv": 440944000.0,
      "pnl": 146334880.0,
      "pnl_ratio": 0.4967085879758237
    },
    {
      "symbol": "018260",
      "name": "삼성에스디에스",
      "side": "LONG",
      "qty": 1150.0,
      "avg_price": 176700.0,
      "group": "삼성에스디에스",
      "last_price": 175600,
      "exposure": 203205000.0,
      "mv": 201940000.0,
      "pnl": -1265000.0,
      "pnl_ratio": -0.00622524052065648
    }
  ],
  "total_exposure": 4192960337.0,
  "total_pnl": 2140082963.0,
  "total_pnl_ratio": 0.5103990476883922,
  "usd_krw": 1454.176219,
  "wti": 95.94999694824219
}