{
  "as_of": "2026-03-05 10:51:39",
  "currency": "KRW",
  "positions": [
    {
      "symbol": "033240",
      "name": "자화전자",
      "side": "LONG",
      "qty": 2860.0,
      "avg_price": 32695.0,
      "group": "자화전자",
      "last_price": 35150,
      "exposure": 93507700.0,
      "mv": 100529000.0,
      "pnl": 7021300.0,
      "pnl_ratio": 0.07508793393485243
    },
    {
      "symbol": "035720",
      "name": "카카오",
      "side": "LONG",
      "qty": 1580.0,
      "avg_price": 62620.0,
      "group": "카카오",
      "last_price": 50850,
      "exposure": 98939600.0,
      "mv": 80343000.0,
      "pnl": -18596600.0,
      "pnl_ratio": -0.18795911849249441
    },
    {
      "symbol": "440110",
      "name": "파두",
      "side": "LONG",
      "qty": 29000.0,
      "avg_price": 19120.0,
      "group": "파두",
      "last_price": 61300,
      "exposure": 554480000.0,
      "mv": 1777700000.0,
      "pnl": 1223220000.0,
      "pnl_ratio": 2.2060669456066946
    },
    {
      "symbol": "180640",
      "name": "한진칼",
      "side": "LONG",
      "qty": 830.0,
      "avg_price": 116319.0,
      "group": "한진칼",
      "last_price": 120900,
      "exposure": 96544770.0,
      "mv": 100347000.0,
      "pnl": 3802230.0,
      "pnl_ratio": 0.039383075851752505
    },
    {
      "symbol": "000210",
      "name": "DL",
      "side": "LONG",
      "qty": 7183.0,
      "avg_price": 56496.0,
      "group": "DL",
      "last_price": 41700,
      "exposure": 405810768.0,
      "mv": 299531100.0,
      "pnl": -106279668.0,
      "pnl_ratio": -0.2618946474086661
    },
    {
      "symbol": "373220",
      "name": "LG에너지솔루션",
      "side": "LONG",
      "qty": 710.0,
      "avg_price": 423058.0,
      "group": "LG에너지솔루션",
      "last_price": 370000,
      "exposure": 300371180.0,
      "mv": 262700000.0,
      "pnl": -37671180.0,
      "pnl_ratio": -0.12541542767185587
    },
    {
      "symbol": "005935",
      "name": "삼성전자우",
      "side": "LONG",
      "qty": 1600.0,
      "avg_price": 120631.0,
      "group": "삼성전자우",
      "last_price": 125700,
      "exposure": 193009600.0,
      "mv": 201120000.0,
      "pnl": 8110400.0,
      "pnl_ratio": 0.04202070777826595
    },
    {
      "symbol": "018260",
      "name": "삼성에스디에스",
      "side": "LONG",
      "qty": 1150.0,
      "avg_price": 176700.0,
      "group": "삼성에스디에스",
      "last_price": 165800,
      "exposure": 203205000.0,
      "mv": 190670000.0,
      "pnl": -12535000.0,
      "pnl_ratio": -0.06168647425014148
    }
  ],
  "total_exposure": 1945868618.0,
  "total_pnl": 1067071482.0,
  "total_pnl_ratio": 0.5483779696785264
}