{
  "as_of": "2025-10-08 14:22:05",
  "currency": "KRW",
  "positions": [
    {
      "symbol": "061040",
      "name": "알에프텍",
      "side": "LONG",
      "qty": 10370.0,
      "avg_price": 10370.0004,
      "group": "알에프텍",
      "last_price": 2400,
      "exposure": 107536904.148,
      "mv": 24888000.0,
      "pnl": -82648904.148,
      "pnl_ratio": -0.768563171897274
    },
    {
      "symbol": "018260",
      "name": "삼성SDS",
      "side": "LONG",
      "qty": 1150.0,
      "avg_price": 167970.0,
      "group": "SAMSUNG SDS",
      "last_price": 166700,
      "exposure": 193165500.0,
      "mv": 191705000.0,
      "pnl": -1460500.0,
      "pnl_ratio": -0.007560873965589093
    },
    {
      "symbol": "005935",
      "name": "삼성전자우",
      "side": "LONG",
      "qty": 5050.0,
      "avg_price": 60887.996,
      "group": "삼성전자우",
      "last_price": 70000,
      "exposure": 307484379.8,
      "mv": 353500000.0,
      "pnl": 46015620.2,
      "pnl_ratio": 0.14965189526027428
    },
    {
      "symbol": "005930",
      "name": "삼성전자",
      "side": "LONG",
      "qty": 3520.0,
      "avg_price": 70488.4148,
      "group": "삼성전자",
      "last_price": 89000,
      "exposure": 248119220.096,
      "mv": 313280000.0,
      "pnl": 65160779.90400001,
      "pnl_ratio": 0.26261883250635965
    },
    {
      "symbol": "000210",
      "name": "DL",
      "side": "LONG",
      "qty": 7183.0,
      "avg_price": 56496.0,
      "group": "DL",
      "last_price": 36550,
      "exposure": 405810768.0,
      "mv": 262538650.0,
      "pnl": -143272118.0,
      "pnl_ratio": -0.3530515434721042
    },
    {
      "symbol": "000725",
      "name": "현대건설우",
      "side": "LONG",
      "qty": 32.0,
      "avg_price": 88100.0,
      "group": "현대건설우",
      "last_price": 51200,
      "exposure": 2819200.0,
      "mv": 1638400.0,
      "pnl": -1180800.0,
      "pnl_ratio": -0.4188422247446084
    },
    {
      "symbol": "034220",
      "name": "LGD",
      "side": "LONG",
      "qty": 20000.0,
      "avg_price": 12322.75,
      "group": "LGD",
      "last_price": 14580,
      "exposure": 246455000.0,
      "mv": 291600000.0,
      "pnl": 45145000.0,
      "pnl_ratio": 0.18317745633077032
    },
    {
      "symbol": "009150",
      "name": "SEMCO",
      "side": "LONG",
      "qty": 2800.0,
      "avg_price": 137483.5714,
      "group": "SEMCO",
      "last_price": 195800,
      "exposure": 384953999.91999996,
      "mv": 548240000.0,
      "pnl": 163286000.08000004,
      "pnl_ratio": 0.424170160886583
    },
    {
      "symbol": "307950",
      "name": "HYUNDAI AUTOEVER",
      "side": "LONG",
      "qty": 3230.0,
      "avg_price": 134405.7985,
      "group": "HYUNDAI AUTOEVER",
      "last_price": 153300,
      "exposure": 434130729.15500003,
      "mv": 495159000.0,
      "pnl": 61028270.844999984,
      "pnl_ratio": 0.140575791452926
    },
    {
      "symbol": "274090",
      "name": "켄코아에어로스페이스",
      "side": "LONG",
      "qty": 25000.0,
      "avg_price": 13165.48,
      "group": "켄코아에어로스페이스",
      "last_price": 10710,
      "exposure": 329137000.0,
      "mv": 267750000.0,
      "pnl": -61386999.99999999,
      "pnl_ratio": -0.1865089613139817
    },
    {
      "symbol": "117460",
      "name": "KODEX에너지화학",
      "side": "LONG",
      "qty": 31125.0,
      "avg_price": 11600.8635,
      "group": "KODEX에너지화학",
      "last_price": 11765,
      "exposure": 361076876.4375,
      "mv": 366185625.0,
      "pnl": 5108748.562500017,
      "pnl_ratio": 0.01414864505560302
    },
    {
      "symbol": "440110",
      "name": "FADU",
      "side": "LONG",
      "qty": 29000.0,
      "avg_price": 19120.0,
      "group": "FADU",
      "last_price": 22750,
      "exposure": 554480000.0,
      "mv": 659750000.0,
      "pnl": 105270000.0,
      "pnl_ratio": 0.18985355648535565
    },
    {
      "symbol": "034020",
      "name": "두산에너빌리티",
      "side": "LONG",
      "qty": 4500.0,
      "avg_price": 63314.3333,
      "group": "두산에너빌리티",
      "last_price": 64800,
      "exposure": 284914499.84999996,
      "mv": 291600000.0,
      "pnl": 6685500.150000007,
      "pnl_ratio": 0.02346493475593467
    }
  ],
  "total_exposure": 3860084077.4065,
  "total_pnl": 207750597.59350005,
  "total_pnl_ratio": 0.053820226043646904
}